setup.py
django_moreviews.egg-info/PKG-INFO
django_moreviews.egg-info/SOURCES.txt
django_moreviews.egg-info/dependency_links.txt
django_moreviews.egg-info/top_level.txt
moreviews/__init__.py
moreviews/editviews.py