Metadata-Version: 1.0
Name: django-moreviews
Version: 0.1
Summary: Django class-based views that complement the built-in ones.
Home-page: http://tartarus.org/james/computers/django/
Author: James Aylett
Author-email: james@tartarus.org
License: MIT
Platform: UNKNOWN
